{
  "query": "plastic straws",
  "site": "twitter.com",
  "time_range": "2019-06-27..2019-12-26",
  "title": "BostonMarriage (@Boston_Married) | Twitter",
  "href": "https://twitter.com/Boston_Married",
  "body": "The latest Tweets from BostonMarriage (@Boston_Married). Thinking things through. Personally and politically no fixed address. Applied feminism. Big Dyke Energy. Australia",
  "readable_content": "**boston married** (2023-10-04):\n@Boston_Married\nWe are just keeping this cruelty hidden, by proudly saying we don't allow euthanasia for people in these circumstances, and offering all these social housing campaigns to lie to the electorate that enough is being done. \nTo her credit, the lady acknowledged this",
  "summary": null,
  "sentiment": null
}