{
  "query": "plastic pollution",
  "site": "reddit.com",
  "time_range": "2015-01-01..2015-07-02",
  "title": "South Korea Confirms 2 More Deaths in MERS Outbreak : r/worldnews - Reddit",
  "href": "https://www.reddit.com/r/worldnews/comments/38nhlz/south_korea_confirms_2_more_deaths_in_mers/",
  "body": "34M subscribers in the worldnews community. A place for major news from around the world, excluding US-internal news.",
  "textContent": "South Korea Confirms 2 More Deaths in MERS Outbreak : r/worldnews\nOpen menu\nReddit Recap\nLog In\nExpand user menu\nGo to worldnews\nr/worldnews\n•\n9 yr. ago\nhelpmyduck\nSouth Korea Confirms 2 More Deaths in MERS Outbreak\nnytimes.com\nOpen\nArchived post. New comments cannot be posted and votes cannot be cast.\nsurfair.com\nLearn More\nSort by:\nonly_response_needed\n•\n9 yr. ago\n\nbringing the total number of MERS cases in South Korea to 41\n\nNot much of an \"outbreak\". Though, it is a typical Korean pandemic.\n\n \n5\nRank by size \nRelated\nWorld News\nforward\nback\nr/worldnews\nAntony Blinken offers 'unwavering support' for Guyana amid Venezuelan annexation plan\nupi\n512 upvotes · 65 comments\nr/worldnews\nSurgeons perform world’s first eye transplant on man who suffered electric shock\nlbc.co.uk\n853 upvotes · 42 comments\nr/worldnews\nIsrael shares full list of Palestinians to be released in hostage deal\nnewsweek\n2.1K upvotes · 674 comments\nr/worldnews\nMagnitude 7.5 earthquake strikes Mindanao, Philippines\nreuters\n244 upvotes · 13 comments\nr/worldnews\n'Argentina has non-negotiable sovereignty over the Falklands', country's new right-wing president Javier Milei declares\nlbc.co.uk\n12K upvotes · 2.8K comments\nr/worldnews\nVirgin Atlantic completes first long-haul flight fully powered by sustainable fuel\ncnbc\n190 upvotes · 46 comments\nr/worldnews\nLaos is spiraling toward a debt crisis as China looms large.\ncnbc\n153 upvotes · 27 comments\nr/worldnews\nTantric yoga guru Gregorian Bivolaru charged with human trafficking\ntheguardian\n144 upvotes · 14 comments\nr/worldnews\nFalkland's sovereignty 'not up for discussion' Britain warns after new Argentinian president vows to 'get them back'\nlbc.co.uk\n5.1K upvotes · 847 comments\nr/worldnews\nCountries meet in Kenya to thrash out global plastic pollution treaty\ntheguardian\n283 upvotes · 9 comments\nr/worldnews\nWorld to hit 1.4C of warming in record hot 2023\nreuters\n190 upvotes · 49 comments\nr/worldnews\nFirst-ever images prove 'lost echidna' not extinct\nbbc\n378 upvotes · 22 comments\nr/worldnews\nFormer PM David Cameron is introduced to the House of Lords as Baron Cameron of Chipping Norton\nlbc.co.uk\n976 upvotes · 249 comments\nr/worldnews\nThe world briefly smashed through the 2-degree warming limit for the first time ever\ncnn\n939 upvotes · 227 comments\nr/worldnews\nPhilippines considers return to 'fold' of International Criminal Court\nreuters\n90 upvotes · 1 comment\nr/worldnews\nClimate-heating gases reach record highs, UN reports\ntheguardian\n158 upvotes · 12 comments\nr/worldnews\nEU is ill-equipped to meet growing global threats\nreuters\n192 upvotes · 52 comments\nr/worldnews\nGlobal talks to cut plastic waste stall as industry and environmental groups clash\nnpr.org\n108 upvotes · 6 comments\nr/worldnews\nOil prices on track for fourth straight week of declines\nreuters\n263 upvotes · 22 comments\nr/worldnews\nTrapped miners in the Himalayas saved by drill\ncnn\n1.3K upvotes · 79 comments\nr/worldnews\nCurrency clashes sour Russia's oil trade with Asia\nreuters\n171 upvotes · 7 comments\nr/worldnews\nWorld behind on almost every policy required to cut carbon emissions, research finds\ntheguardian\n382 upvotes · 39 comments\nr/worldnews\nNottingham City Council declares itself effectively bankrupt\nbbc\n98 upvotes · 23 comments\nr/worldnews\nFormer Hong Kong activist Agnes Chow flees territory for Canada | Hong Kong\ntheguardian\n406 upvotes · 22 comments\nr/worldnews\nColombia joins international alliance calling for treaty to end use of fossil fuels\ntheguardian\n215 upvotes · 14 comments\nTOP POSTS\nReddit\nreReddit: Top posts of June 5, 2015\nReddit\nreReddit: Top posts of June 2015\nReddit\nreReddit: Top posts of 2015"
}