{
  "query": "plastic straws",
  "site": null,
  "time_range": "2015-01-01..2015-07-02",
  "title": "Tallest Plastic Straw Tower | World Record | Aniruddha Chopadekar",
  "href": "https://recordsetter.com/world-record/tallest-plastic-straw-tower/41024",
  "body": "Aniruddha C. constructed a plastic straw tower 21 feet in height. - may use transparent binding tape - width of tower at base must be no more than nine inches - must follow form of current world record holder - must provide video evidence. Share on Facebook. Share on Twitter. Share link.",
  "textContent": "SET A RECORD!\nEXPLORE RECORDS\nLOG IN / SIGN UP\n \nTallest Plastic Straw Tower\n ANIRUDDHA CHOPADEKAR\n3 likes\nRATE IT:\nLEGENDARY\nFUNNY\nCUTE\nCREATIVE\nGROSS\nIMPRESSIVE\nABOUT\nRULES\nSHARE\n\nNashik, Maharashtra , India / April 22, 2015\n\nAniruddha C. constructed a plastic straw tower 21 feet in height.\n\nTags: wildcard, tallest, tower, drinking straw, plastic straw\n\nCOMMENTS\nSACHIN\n8 YEARS AGO\n\nWell done anirudhaa i am proud you\n\nLIKE\n·\nREPLY\nRESPONSE TO THIS ATTEMPT\nRAVINDRA\n8 YEARS AGO\n\nCongratulation Aniruddha\n\nLIKE\n·\nREPLY\nRESPONSE TO THIS ATTEMPT\n21 feet\nWORLD RECORD\nCHALLENGE IT!\nHISTORY\n21\nORIGINAL\n\nANIRUDDHA on 4/22/2015\n\nRELATED RECORDS\nf\nMost Dollar Coins Stacked On Top Of 3D Glasses While Standing\n\nf\nMost Quarters Balanced On Hand\n\nf\n01:36\nTallest Coffee Cup Tower\n\nf\nTallest Penny Tower Stacked On A Handheld AA Battery\n\nMore Suggestions\nABOUT RECORDSETTER\nSET A RECORD!\nFOR BUSINESSES\nSUBMIT\nCONTACT\nFAQ\nSTORE\nLEGAL\n©RECORDSETTER. ALL RIGHTS RESERVED. 2023."
}