{
  "query": "plastic pollution",
  "site": "reddit.com",
  "time_range": "2015-07-02..2015-12-31",
  "title": "JumpChain - Reddit",
  "href": "https://www.reddit.com/r/JumpChain/",
  "body": "Welcome All Jumpers! This is a Sister subreddit to the makeyourchoice CYOA subreddit. This Subreddit focuses specially on the JumpChain CYOA, where the 'Jumpers' travel across the multiverse visiting both fictional and original worlds in a series of 'Choose your own adventure' templates, each carrying on to the next... Come here for discussion and fanworks from the reddit Jumpers!"
}