{
  "query": "plastic pollution",
  "site": "reddit.com",
  "time_range": "2016-06-30..2016-12-29",
  "title": "Massive tits - Reddit",
  "href": "https://www.reddit.com/r/massivetits/",
  "body": "r/massivetits: A subreddit for sharing pictures of massive tits. If you are claiming a post to be you, it must have [OC] in the title. You may become verified by sending a modmail with pictures of yourself holding a piece of cardboard with your username written (by hand) on it, taken from at least 2 different angles."
}