{
  "query": "plastic straws",
  "site": null,
  "time_range": "2017-12-28..2018-06-28",
  "title": "How Skipping Plastic Straws Can Have a Bigger ... - WorldAtlas",
  "href": "https://www.worldatlas.com/news/how-skipping-plastic-straws-can-have-a-bigger-environmental-impact-than-you-realize.html",
  "body": "Plastic straws are made of polypropylene, which is identified by resin code 5 and usually recyclable. However, due to their small size most facilities cannot process plastic straws, meaning they end up in landfills. The problem with plastic straws does not end here."
}