{
  "query": "plastic pollution",
  "site": null,
  "time_range": "2018-06-28..2018-12-27",
  "title": "Fast facts about plastic pollution - National Geographic",
  "href": "https://www.nationalgeographic.com/science/article/plastics-facts-infographics-ocean-pollution",
  "body": "Learn eight essential facts about the global plastic pollution crisis, from its causes and effects to its solutions and prevention. Find out how plastic is produced, used, recycled, and disposed in different regions and industries, and how it affects the environment and human health."
}