{
  "query": "plastic pollution",
  "site": "reddit.com",
  "time_range": "2019-06-27..2019-12-26",
  "title": "Black and Brown Feet - Reddit",
  "href": "https://www.reddit.com/r/BlackBrownFEET/",
  "body": "Anything with FEET from women of color (BIPOC) are showcased here. This is also somewhat of a bridge between r/ebonyfeet and r/latinafeet. Verified women from both subs are encouraged to post and collab in here. Please read the rules before posting. If posting nudity, mark the post NSFW. Sub icon: u/vindic8d."
}